pikachuwechat/__init__.py
pikachuwechat/pikachuwechat.py
pikachuwechat/modules/__init__.py
pikachuwechat/modules/core/__init__.py
pikachuwechat/modules/core/analysisfriends.py
pikachuwechat/modules/core/antiwithdrawal.py
pikachuwechat/modules/core/autoreply.py
pikachuwechat/modules/utils/__init__.py
pikachuwechat/modules/utils/logger.py
pikachuwechat/modules/utils/misc.py
pikachuwechat-0.1.2.dist-info/LICENSE
pikachuwechat-0.1.2.dist-info/METADATA
pikachuwechat-0.1.2.dist-info/WHEEL
pikachuwechat-0.1.2.dist-info/top_level.txt
pikachuwechat-0.1.2.dist-info/zip-safe
pikachuwechat-0.1.2.dist-info/RECORD
