Metadata-Version: 2.1
Name: pikachuwechat
Version: 0.1.2
Summary: PikachuWeChat: Play WeChat with itchat-uos.
Home-page: https://github.com/CharlesPikachu/pikachuwechat
Author: Zhenchao Jin
Author-email: charlesblwx@gmail.com
License: Apache License 2.0
Platform: UNKNOWN
Classifier: License :: OSI Approved :: Apache Software License
Classifier: Programming Language :: Python :: 3
Classifier: Intended Audience :: Developers
Classifier: Operating System :: OS Independent
License-File: LICENSE
Requires-Dist: itchat-uos
Requires-Dist: pyecharts
